Workbook

Sheet Indice de fragilidad
A1: ÍNDICE DE FRAGILIDAD COMERCIAL
A2: Evalúa qué tan vulnerable es el flujo comercial actual. Puntúa cada dimensión de 1 a 5. | G2: HERRAMIENTA 1
B3: DIMENSIÓN | C3: PREGUNTA | D3: PUNTUACIÓN | E3: 1 | F3: 2 | G3: 3 | H3: 4 | I3: 5
B4: Frecuencia | C4: ¿Qué tan irregular es la entrada de clientes nuevos? | E4: Entradas constantes durante el mes | F4: Flujo relativamente estable | G4: Hay semanas fuertes y semanas vacías | H4: Las ventas llegan de manera muy irregular | I4: Dependo de cierres aislados
B5: Concentración | C5: ¿Qué tanto dependes de pocos clientes o ventas grandes? | E5: Ningún cliente representa una parte crítica | F5: Hay cierta concentración, pero es manejable | G5: Algunos clientes pesan demasiado | H5: Pocos clientes explican gran parte de la facturación | I5: Perder uno o dos clientes compromete el negocio
B6: Predictibilidad | C6: ¿Qué tan difícil es anticipar cuánto facturarás el próximo mes? | E6: Puedo estimar razonablemente la facturación | F6: Tengo cierta visibilidad | G6: La previsión es imprecisa | H6: Cada mes empieza casi desde cero | I6: No tengo idea de cuánto facturaré
B7: Riesgo de entrada | C7: ¿Qué tan difícil es para un cliente nuevo probar tu oferta? | E7: Es fácil y poco riesgoso probar la oferta | F7: El cliente puede entrar con una decisión pequeña | G7: Requiere cierta confianza previa | H7: Supone una inversión o compromiso significativo | I7: El cliente debe apostar fuerte sin habernos probado
B8: Complejidad comercial | C8: ¿Cuánto tienes que explicar para que alguien entienda por qué debe comprarte? | E8: Se entiende en segundos | F8: Requiere una explicación breve | G8: Necesita conversación comercial | H8: Requiere reuniones, propuestas y seguimiento | I8: Necesita un discurso largo para justificar su valor
B9: Recurrencia | C9: ¿Qué tan poca recompra o continuidad existe? | E9: La mayoría recompra o continúa | F9: Existe recurrencia razonable | G9: Hay recompra, pero no está diseñada | H9: La mayoría compra una sola vez | I9: Cada venta exige conseguir un cliente nuevo
B10: Confianza | C10: ¿Qué tanto necesita el prospecto conocerte antes de comprarte? | E10: La propuesta se vende con evidencia clara | F10: La reputación reduce objeciones | G10: La confianza depende parcialmente del fundador | H10: El cliente necesita hablar conmigo | I10: Sin mi reputación personal casi no compran
B11: Capacidad | C11: ¿Qué tanto depende la venta y la entrega de ti? | E11: El equipo vende y entrega sin depender de mí | F11: Intervengo solo en puntos clave | G11: Participo en varias etapas | H11: Soy necesario para vender o entregar | I11: Todo depende directamente de mí
B12: Margen | C12: ¿Qué tan insuficiente es el margen después de considerar todo el esfuerzo? | E12: El margen cubre operación y crecimiento | F12: Es razonable | G12: Es aceptable, pero frágil | H12: El esfuerzo consume gran parte del margen | I12: Facturo, pero casi no gano
B13: RESULTADO | C13: =IF(COUNT(D4:D12)<9,"Completa las 9 respuestas",IF(D13<=16,"Portafolio relativamente sano",IF(D13<=24,"Flujo vulnerable",IF(D13<=32,"Dependencia de ventas esporádicas","Modelo comercial frágil")))) -> Completa las 9 respuestas | D13: =IF(COUNT(D4:D12)=0,"",SUM(D4:D12))
B14: ACCIÓN SUGERIDA | C14: =IF(COUNT(D4:D12)<9,"Completa el diagnóstico antes de decidir",IF(D13<=16,"Protege lo que funciona y diseña un siguiente nivel de crecimiento",IF(D13<=24,"Diseña al menos un producto PAN que estabilice la entrada de clientes",IF(D13<=32,"Reduce concentración, simplifica la compra y crea recurrencia","Rediseña el portafolio: hoy el negocio depende de cierres aislados y del fundador")))) -> Completa el diagnóstico antes de decidir
B16: LECTURA DEL ÍNDICE | C16: 9–16 | D16: 17–24 | E16: 25–32 | F16: 33–45
B17: Diagnóstico | C17: Relativamente sano | D17: Flujo vulnerable | E17: Ventas esporádicas | F17: Modelo frágil
B18: Foco | C18: Proteger y escalar | D18: Crear flujo | E18: Reducir dependencia | F18: Rediseñar portafolio

Sheet Inventario del Portafolio
A1: INVENTARIO DEL PORTAFOLIO
A2: Haz visible de dónde entra el dinero, cuánto trabajo exige cada oferta y qué papel cumple realmente. | K2: HERRAMIENTA 2
A3: INGRESO MENSUAL DEL PORTAFOLIO | D3: CONCENTRACIÓN DEL PRODUCTO MAYOR | G3: OFERTAS RECURRENTES | J3: HORAS MENSUALES DE ENTREGA
A4: =SUM(E6:E15) -> 0 | D4: =IFERROR(MAX(J6:J15),0) -> 0 | G4: =COUNTIF(F6:F15,"Sí") -> 0 | J4: =SUM(H6:H15) -> 0
A5: # | B5: Producto / servicio | C5: Precio promedio | D5: Ventas mensuales | E5: Ingreso mensual | F5: ¿Recurrente? | G5: Horas por unidad | H5: Horas mensuales | I5: Responsable | J5: % facturación | K5: Rol preliminar | L5: Oferta siguiente | M5: Observaciones
A6: 1 | E6: =IF(OR(C6="",D6=""),"",C6*D6) | H6: =IF(OR(D6="",G6=""),"",D6*G6) | J6: =IFERROR(E6/SUM($E$6:$E$15),0) -> 0
A7: 2 | E7: =IF(OR(C7="",D7=""),"",C7*D7) | H7: =IF(OR(D7="",G7=""),"",D7*G7) | J7: =IFERROR(E7/SUM($E$6:$E$15),0) -> 0
A8: 3 | E8: =IF(OR(C8="",D8=""),"",C8*D8) | H8: =IF(OR(D8="",G8=""),"",D8*G8) | J8: =IFERROR(E8/SUM($E$6:$E$15),0) -> 0
A9: 4 | E9: =IF(OR(C9="",D9=""),"",C9*D9) | H9: =IF(OR(D9="",G9=""),"",D9*G9) | J9: =IFERROR(E9/SUM($E$6:$E$15),0) -> 0
A10: 5 | E10: =IF(OR(C10="",D10=""),"",C10*D10) | H10: =IF(OR(D10="",G10=""),"",D10*G10) | J10: =IFERROR(E10/SUM($E$6:$E$15),0) -> 0
A11: 6 | E11: =IF(OR(C11="",D11=""),"",C11*D11) | H11: =IF(OR(D11="",G11=""),"",D11*G11) | J11: =IFERROR(E11/SUM($E$6:$E$15),0) -> 0
A12: 7 | E12: =IF(OR(C12="",D12=""),"",C12*D12) | H12: =IF(OR(D12="",G12=""),"",D12*G12) | J12: =IFERROR(E12/SUM($E$6:$E$15),0) -> 0
A13: 8 | E13: =IF(OR(C13="",D13=""),"",C13*D13) | H13: =IF(OR(D13="",G13=""),"",D13*G13) | J13: =IFERROR(E13/SUM($E$6:$E$15),0) -> 0
A14: 9 | E14: =IF(OR(C14="",D14=""),"",C14*D14) | H14: =IF(OR(D14="",G14=""),"",D14*G14) | J14: =IFERROR(E14/SUM($E$6:$E$15),0) -> 0
A15: 10 | E15: =IF(OR(C15="",D15=""),"",C15*D15) | H15: =IF(OR(D15="",G15=""),"",D15*G15) | J15: =IFERROR(E15/SUM($E$6:$E$15),0) -> 0
A16: TOTAL | E16: =SUM(E6:E15) -> 0 | H16: =SUM(H6:H15) -> 0 | J16: =SUM(J6:J15) -> 0

Sheet Índice PAN
A1: ÍNDICE PAN
A2: Mide qué tan bien cumple cada oferta la función de generar flujo y facilitar la primera compra. | H2: HERRAMIENTA 4
A4: # | B4: Producto / servicio | C4: Facilidad de entender | D4: Bajo riesgo percibido | E4: Frecuencia de compra | F4: Ciclo de venta corto | G4: Baja confianza previa | H4: TOTAL | I4: DIAGNÓSTICO | J4: ACCIÓN RECOMENDADA
A5: 1 | B5: =IF('Inventario del Portafolio'!B6="","",'Inventario del Portafolio'!B6) | H5: =IF(COUNT(C5:G5)<5,"",SUM(C5:G5)) | I5: =IF(B5="","",IF(H5="","Completa puntajes",IF(H5<=10,"No funciona como PAN",IF(H5<=15,"PAN débil",IF(H5<=20,"Buen PAN","Excelente PAN"))))) | J5: =IF(I5="","",IF(I5="No funciona como PAN","No usar como oferta de entrada",IF(I5="PAN débil","Simplificar y reducir el riesgo",IF(I5="Buen PAN","Estandarizar y conectar con una TORTA","Escalar adquisición y medir conversión"))))
A6: 2 | B6: =IF('Inventario del Portafolio'!B7="","",'Inventario del Portafolio'!B7) | H6: =IF(COUNT(C6:G6)<5,"",SUM(C6:G6)) | I6: =IF(B6="","",IF(H6="","Completa puntajes",IF(H6<=10,"No funciona como PAN",IF(H6<=15,"PAN débil",IF(H6<=20,"Buen PAN","Excelente PAN"))))) | J6: =IF(I6="","",IF(I6="No funciona como PAN","No usar como oferta de entrada",IF(I6="PAN débil","Simplificar y reducir el riesgo",IF(I6="Buen PAN","Estandarizar y conectar con una TORTA","Escalar adquisición y medir conversión"))))
A7: 3 | B7: =IF('Inventario del Portafolio'!B8="","",'Inventario del Portafolio'!B8) | H7: =IF(COUNT(C7:G7)<5,"",SUM(C7:G7)) | I7: =IF(B7="","",IF(H7="","Completa puntajes",IF(H7<=10,"No funciona como PAN",IF(H7<=15,"PAN débil",IF(H7<=20,"Buen PAN","Excelente PAN"))))) | J7: =IF(I7="","",IF(I7="No funciona como PAN","No usar como oferta de entrada",IF(I7="PAN débil","Simplificar y reducir el riesgo",IF(I7="Buen PAN","Estandarizar y conectar con una TORTA","Escalar adquisición y medir conversión"))))
A8: 4 | B8: =IF('Inventario del Portafolio'!B9="","",'Inventario del Portafolio'!B9) | H8: =IF(COUNT(C8:G8)<5,"",SUM(C8:G8)) | I8: =IF(B8="","",IF(H8="","Completa puntajes",IF(H8<=10,"No funciona como PAN",IF(H8<=15,"PAN débil",IF(H8<=20,"Buen PAN","Excelente PAN"))))) | J8: =IF(I8="","",IF(I8="No funciona como PAN","No usar como oferta de entrada",IF(I8="PAN débil","Simplificar y reducir el riesgo",IF(I8="Buen PAN","Estandarizar y conectar con una TORTA","Escalar adquisición y medir conversión"))))
A9: 5 | B9: =IF('Inventario del Portafolio'!B10="","",'Inventario del Portafolio'!B10) | H9: =IF(COUNT(C9:G9)<5,"",SUM(C9:G9)) | I9: =IF(B9="","",IF(H9="","Completa puntajes",IF(H9<=10,"No funciona como PAN",IF(H9<=15,"PAN débil",IF(H9<=20,"Buen PAN","Excelente PAN"))))) | J9: =IF(I9="","",IF(I9="No funciona como PAN","No usar como oferta de entrada",IF(I9="PAN débil","Simplificar y reducir el riesgo",IF(I9="Buen PAN","Estandarizar y conectar con una TORTA","Escalar adquisición y medir conversión"))))
A10: 6 | B10: =IF('Inventario del Portafolio'!B11="","",'Inventario del Portafolio'!B11) | H10: =IF(COUNT(C10:G10)<5,"",SUM(C10:G10)) | I10: =IF(B10="","",IF(H10="","Completa puntajes",IF(H10<=10,"No funciona como PAN",IF(H10<=15,"PAN débil",IF(H10<=20,"Buen PAN","Excelente PAN"))))) | J10: =IF(I10="","",IF(I10="No funciona como PAN","No usar como oferta de entrada",IF(I10="PAN débil","Simplificar y reducir el riesgo",IF(I10="Buen PAN","Estandarizar y conectar con una TORTA","Escalar adquisición y medir conversión"))))
A11: 7 | B11: =IF('Inventario del Portafolio'!B12="","",'Inventario del Portafolio'!B12) | H11: =IF(COUNT(C11:G11)<5,"",SUM(C11:G11)) | I11: =IF(B11="","",IF(H11="","Completa puntajes",IF(H11<=10,"No funciona como PAN",IF(H11<=15,"PAN débil",IF(H11<=20,"Buen PAN","Excelente PAN"))))) | J11: =IF(I11="","",IF(I11="No funciona como PAN","No usar como oferta de entrada",IF(I11="PAN débil","Simplificar y reducir el riesgo",IF(I11="Buen PAN","Estandarizar y conectar con una TORTA","Escalar adquisición y medir conversión"))))
A12: 8 | B12: =IF('Inventario del Portafolio'!B13="","",'Inventario del Portafolio'!B13) | H12: =IF(COUNT(C12:G12)<5,"",SUM(C12:G12)) | I12: =IF(B12="","",IF(H12="","Completa puntajes",IF(H12<=10,"No funciona como PAN",IF(H12<=15,"PAN débil",IF(H12<=20,"Buen PAN","Excelente PAN"))))) | J12: =IF(I12="","",IF(I12="No funciona como PAN","No usar como oferta de entrada",IF(I12="PAN débil","Simplificar y reducir el riesgo",IF(I12="Buen PAN","Estandarizar y conectar con una TORTA","Escalar adquisición y medir conversión"))))
A13: 9 | B13: =IF('Inventario del Portafolio'!B14="","",'Inventario del Portafolio'!B14) | H13: =IF(COUNT(C13:G13)<5,"",SUM(C13:G13)) | I13: =IF(B13="","",IF(H13="","Completa puntajes",IF(H13<=10,"No funciona como PAN",IF(H13<=15,"PAN débil",IF(H13<=20,"Buen PAN","Excelente PAN"))))) | J13: =IF(I13="","",IF(I13="No funciona como PAN","No usar como oferta de entrada",IF(I13="PAN débil","Simplificar y reducir el riesgo",IF(I13="Buen PAN","Estandarizar y conectar con una TORTA","Escalar adquisición y medir conversión"))))
A14: 10 | B14: =IF('Inventario del Portafolio'!B15="","",'Inventario del Portafolio'!B15) | H14: =IF(COUNT(C14:G14)<5,"",SUM(C14:G14)) | I14: =IF(B14="","",IF(H14="","Completa puntajes",IF(H14<=10,"No funciona como PAN",IF(H14<=15,"PAN débil",IF(H14<=20,"Buen PAN","Excelente PAN"))))) | J14: =IF(I14="","",IF(I14="No funciona como PAN","No usar como oferta de entrada",IF(I14="PAN débil","Simplificar y reducir el riesgo",IF(I14="Buen PAN","Estandarizar y conectar con una TORTA","Escalar adquisición y medir conversión"))))
B17: CRITERIO | C17: 1 | D17: 5
B18: Facilidad de entender | C18: Difícil de explicar | D18: Se entiende de inmediato
B19: Bajo riesgo percibido | C19: El cliente siente que apuesta fuerte | D19: Probarlo se siente seguro
B20: Frecuencia de compra | C20: Compra excepcional | D20: Compra frecuente o recurrente
B21: Ciclo de venta corto | C21: Decisión lenta y compleja | D21: Decisión rápida
B22: Baja confianza previa | C22: Necesita conocer al fundador | D22: La evidencia basta para decidir

Sheet Índice TORTA
A1: ÍNDICE TORTA
A2: Mide qué tan bien cumple cada oferta la función de generar margen, diferenciación y crecimiento. | H2: HERRAMIENTA 5
A4: # | B4: Producto / servicio | C4: Rentabilidad por hora | D4: Margen unitario | E4: Contribución estratégica | F4: Potencial de diferenciación | G4: Potencial de escalamiento | H4: TOTAL | I4: DIAGNÓSTICO | J4: ACCIÓN RECOMENDADA
A5: 1 | B5: =IF('Inventario del Portafolio'!B6="","",'Inventario del Portafolio'!B6) | H5: =IF(COUNT(C5:G5)<5,"",SUM(C5:G5)) | I5: =IF(B5="","",IF(H5="","Completa puntajes",IF(H5<=10,"Poco valor estratégico",IF(H5<=15,"TORTA débil",IF(H5<=20,"Buena TORTA","Excelente TORTA"))))) | J5: =IF(I5="","",IF(I5="Poco valor estratégico","Rediseñar o retirar",IF(I5="TORTA débil","Mejorar margen o diferenciación",IF(I5="Buena TORTA","Fortalecer la ruta de entrada","Proteger, escalar y sistematizar"))))
A6: 2 | B6: =IF('Inventario del Portafolio'!B7="","",'Inventario del Portafolio'!B7) | H6: =IF(COUNT(C6:G6)<5,"",SUM(C6:G6)) | I6: =IF(B6="","",IF(H6="","Completa puntajes",IF(H6<=10,"Poco valor estratégico",IF(H6<=15,"TORTA débil",IF(H6<=20,"Buena TORTA","Excelente TORTA"))))) | J6: =IF(I6="","",IF(I6="Poco valor estratégico","Rediseñar o retirar",IF(I6="TORTA débil","Mejorar margen o diferenciación",IF(I6="Buena TORTA","Fortalecer la ruta de entrada","Proteger, escalar y sistematizar"))))
A7: 3 | B7: =IF('Inventario del Portafolio'!B8="","",'Inventario del Portafolio'!B8) | H7: =IF(COUNT(C7:G7)<5,"",SUM(C7:G7)) | I7: =IF(B7="","",IF(H7="","Completa puntajes",IF(H7<=10,"Poco valor estratégico",IF(H7<=15,"TORTA débil",IF(H7<=20,"Buena TORTA","Excelente TORTA"))))) | J7: =IF(I7="","",IF(I7="Poco valor estratégico","Rediseñar o retirar",IF(I7="TORTA débil","Mejorar margen o diferenciación",IF(I7="Buena TORTA","Fortalecer la ruta de entrada","Proteger, escalar y sistematizar"))))
A8: 4 | B8: =IF('Inventario del Portafolio'!B9="","",'Inventario del Portafolio'!B9) | H8: =IF(COUNT(C8:G8)<5,"",SUM(C8:G8)) | I8: =IF(B8="","",IF(H8="","Completa puntajes",IF(H8<=10,"Poco valor estratégico",IF(H8<=15,"TORTA débil",IF(H8<=20,"Buena TORTA","Excelente TORTA"))))) | J8: =IF(I8="","",IF(I8="Poco valor estratégico","Rediseñar o retirar",IF(I8="TORTA débil","Mejorar margen o diferenciación",IF(I8="Buena TORTA","Fortalecer la ruta de entrada","Proteger, escalar y sistematizar"))))
A9: 5 | B9: =IF('Inventario del Portafolio'!B10="","",'Inventario del Portafolio'!B10) | H9: =IF(COUNT(C9:G9)<5,"",SUM(C9:G9)) | I9: =IF(B9="","",IF(H9="","Completa puntajes",IF(H9<=10,"Poco valor estratégico",IF(H9<=15,"TORTA débil",IF(H9<=20,"Buena TORTA","Excelente TORTA"))))) | J9: =IF(I9="","",IF(I9="Poco valor estratégico","Rediseñar o retirar",IF(I9="TORTA débil","Mejorar margen o diferenciación",IF(I9="Buena TORTA","Fortalecer la ruta de entrada","Proteger, escalar y sistematizar"))))
A10: 6 | B10: =IF('Inventario del Portafolio'!B11="","",'Inventario del Portafolio'!B11) | H10: =IF(COUNT(C10:G10)<5,"",SUM(C10:G10)) | I10: =IF(B10="","",IF(H10="","Completa puntajes",IF(H10<=10,"Poco valor estratégico",IF(H10<=15,"TORTA débil",IF(H10<=20,"Buena TORTA","Excelente TORTA"))))) | J10: =IF(I10="","",IF(I10="Poco valor estratégico","Rediseñar o retirar",IF(I10="TORTA débil","Mejorar margen o diferenciación",IF(I10="Buena TORTA","Fortalecer la ruta de entrada","Proteger, escalar y sistematizar"))))
A11: 7 | B11: =IF('Inventario del Portafolio'!B12="","",'Inventario del Portafolio'!B12) | H11: =IF(COUNT(C11:G11)<5,"",SUM(C11:G11)) | I11: =IF(B11="","",IF(H11="","Completa puntajes",IF(H11<=10,"Poco valor estratégico",IF(H11<=15,"TORTA débil",IF(H11<=20,"Buena TORTA","Excelente TORTA"))))) | J11: =IF(I11="","",IF(I11="Poco valor estratégico","Rediseñar o retirar",IF(I11="TORTA débil","Mejorar margen o diferenciación",IF(I11="Buena TORTA","Fortalecer la ruta de entrada","Proteger, escalar y sistematizar"))))
A12: 8 | B12: =IF('Inventario del Portafolio'!B13="","",'Inventario del Portafolio'!B13) | H12: =IF(COUNT(C12:G12)<5,"",SUM(C12:G12)) | I12: =IF(B12="","",IF(H12="","Completa puntajes",IF(H12<=10,"Poco valor estratégico",IF(H12<=15,"TORTA débil",IF(H12<=20,"Buena TORTA","Excelente TORTA"))))) | J12: =IF(I12="","",IF(I12="Poco valor estratégico","Rediseñar o retirar",IF(I12="TORTA débil","Mejorar margen o diferenciación",IF(I12="Buena TORTA","Fortalecer la ruta de entrada","Proteger, escalar y sistematizar"))))
A13: 9 | B13: =IF('Inventario del Portafolio'!B14="","",'Inventario del Portafolio'!B14) | H13: =IF(COUNT(C13:G13)<5,"",SUM(C13:G13)) | I13: =IF(B13="","",IF(H13="","Completa puntajes",IF(H13<=10,"Poco valor estratégico",IF(H13<=15,"TORTA débil",IF(H13<=20,"Buena TORTA","Excelente TORTA"))))) | J13: =IF(I13="","",IF(I13="Poco valor estratégico","Rediseñar o retirar",IF(I13="TORTA débil","Mejorar margen o diferenciación",IF(I13="Buena TORTA","Fortalecer la ruta de entrada","Proteger, escalar y sistematizar"))))
A14: 10 | B14: =IF('Inventario del Portafolio'!B15="","",'Inventario del Portafolio'!B15) | H14: =IF(COUNT(C14:G14)<5,"",SUM(C14:G14)) | I14: =IF(B14="","",IF(H14="","Completa puntajes",IF(H14<=10,"Poco valor estratégico",IF(H14<=15,"TORTA débil",IF(H14<=20,"Buena TORTA","Excelente TORTA"))))) | J14: =IF(I14="","",IF(I14="Poco valor estratégico","Rediseñar o retirar",IF(I14="TORTA débil","Mejorar margen o diferenciación",IF(I14="Buena TORTA","Fortalecer la ruta de entrada","Proteger, escalar y sistematizar"))))
B17: CRITERIO | C17: 1 | D17: 5
B18: Rentabilidad por hora | C18: Baja | D18: Alta
B19: Margen unitario | C19: Bajo | D19: Alto
B20: Contribución estratégica | C20: Apenas aporta al crecimiento | D20: Es crítica para el futuro
B21: Potencial de diferenciación | C21: Fácil de comparar o copiar | D21: Difícil de sustituir
B22: Potencial de escalamiento | C22: Crece solo con más horas | D22: Crece sin depender linealmente de horas

Sheet Mapa estratégico
A1: MAPA ESTRATÉGICO DEL PORTAFOLIO
A2: Cruza capacidad de generar flujo (PAN) con valor estratégico (TORTA). El cuadrante define la decisión. | R2: HERRAMIENTA 6
M3: VALOR ESTRATÉGICO →
A4: # | B4: Producto / servicio | C4: Ingreso mensual | D4: % facturación | E4: Índice PAN | F4: Diagnóstico PAN | G4: Índice TORTA | H4: Diagnóstico TORTA | I4: CUADRANTE | J4: DECISIÓN ESTRATÉGICA | K4: PRIORIDAD | U4: Total | V4: Diagnóstico
A5: 1 | B5: =IF('Inventario del Portafolio'!B6="","",'Inventario del Portafolio'!B6) | C5: =IF(B5="","",'Inventario del Portafolio'!E6) | D5: =IF(B5="","",'Inventario del Portafolio'!J6) | E5: =IF(B5="","",'Índice PAN'!H5) | F5: =IF(B5="","",'Índice PAN'!I5) | G5: =IF(B5="","",'Índice TORTA'!H5) | H5: =IF(B5="","",'Índice TORTA'!I5) | I5: =IF(B5="","",IF(OR(E5="",G5=""),"SIN EVALUAR",IF(AND(E5>=16,G5>=16),"ESTRELLA",IF(AND(E5>=16,G5<16),"PAN",IF(AND(E5<16,G5>=16),"TORTA","LASTRE"))))) | J5: =IF(I5="","",IF(I5="ESTRELLA","Escalar y proteger",IF(I5="PAN","Conectar con una TORTA",IF(I5="TORTA","Crear un PAN de entrada",IF(I5="LASTRE","Rediseñar o retirar","Completar evaluación"))))) | K5: =IF(B5="","",IF(I5="ESTRELLA","1 - Alta",IF(I5="PAN","2 - Media",IF(I5="TORTA","2 - Media",IF(I5="LASTRE","1 - Alta","3 - Pendiente"))))) | L5: FLUJO → | M5: PAN Flujo alto / Valor bajo Conectar con una TORTA | Q5: ESTRELLA Flujo alto / Valor alto Escalar y proteger | U5: =SUM(P5:T5) -> 0 | V5: =IF(U5="","",IF(U5<5,"Revisar puntaje",IF(U5<=10,"Poco valor estratégico",IF(U5<=15,"Torta débil",IF(U5<=20,"Buena torta","Excelente torta"))))) -> Revisar puntaje
A6: 2 | B6: =IF('Inventario del Portafolio'!B7="","",'Inventario del Portafolio'!B7) | C6: =IF(B6="","",'Inventario del Portafolio'!E7) | D6: =IF(B6="","",'Inventario del Portafolio'!J7) | E6: =IF(B6="","",'Índice PAN'!H6) | F6: =IF(B6="","",'Índice PAN'!I6) | G6: =IF(B6="","",'Índice TORTA'!H6) | H6: =IF(B6="","",'Índice TORTA'!I6) | I6: =IF(B6="","",IF(OR(E6="",G6=""),"SIN EVALUAR",IF(AND(E6>=16,G6>=16),"ESTRELLA",IF(AND(E6>=16,G6<16),"PAN",IF(AND(E6<16,G6>=16),"TORTA","LASTRE"))))) | J6: =IF(I6="","",IF(I6="ESTRELLA","Escalar y proteger",IF(I6="PAN","Conectar con una TORTA",IF(I6="TORTA","Crear un PAN de entrada",IF(I6="LASTRE","Rediseñar o retirar","Completar evaluación"))))) | K6: =IF(B6="","",IF(I6="ESTRELLA","1 - Alta",IF(I6="PAN","2 - Media",IF(I6="TORTA","2 - Media",IF(I6="LASTRE","1 - Alta","3 - Pendiente"))))) | N6: =SUM(I6:M6) -> 0 | O6: =IF(N6="","",IF(N6<5,"Revisar puntaje",IF(N6<=10,"No funciona como pan",IF(N6<=15,"Pan débil",IF(N6<=20,"Buen producto pan","Excelente producto pan"))))) -> Revisar puntaje | U6: =SUM(P6:T6) -> 0 | V6: =IF(U6="","",IF(U6<5,"Revisar puntaje",IF(U6<=10,"Poco valor estratégico",IF(U6<=15,"Torta débil",IF(U6<=20,"Buena torta","Excelente torta"))))) -> Revisar puntaje
A7: 3 | B7: =IF('Inventario del Portafolio'!B8="","",'Inventario del Portafolio'!B8) | C7: =IF(B7="","",'Inventario del Portafolio'!E8) | D7: =IF(B7="","",'Inventario del Portafolio'!J8) | E7: =IF(B7="","",'Índice PAN'!H7) | F7: =IF(B7="","",'Índice PAN'!I7) | G7: =IF(B7="","",'Índice TORTA'!H7) | H7: =IF(B7="","",'Índice TORTA'!I7) | I7: =IF(B7="","",IF(OR(E7="",G7=""),"SIN EVALUAR",IF(AND(E7>=16,G7>=16),"ESTRELLA",IF(AND(E7>=16,G7<16),"PAN",IF(AND(E7<16,G7>=16),"TORTA","LASTRE"))))) | J7: =IF(I7="","",IF(I7="ESTRELLA","Escalar y proteger",IF(I7="PAN","Conectar con una TORTA",IF(I7="TORTA","Crear un PAN de entrada",IF(I7="LASTRE","Rediseñar o retirar","Completar evaluación"))))) | K7: =IF(B7="","",IF(I7="ESTRELLA","1 - Alta",IF(I7="PAN","2 - Media",IF(I7="TORTA","2 - Media",IF(I7="LASTRE","1 - Alta","3 - Pendiente"))))) | N7: =SUM(I7:M7) -> 0 | O7: =IF(N7="","",IF(N7<5,"Revisar puntaje",IF(N7<=10,"No funciona como pan",IF(N7<=15,"Pan débil",IF(N7<=20,"Buen producto pan","Excelente producto pan"))))) -> Revisar puntaje | U7: =SUM(P7:T7) -> 0 | V7: =IF(U7="","",IF(U7<5,"Revisar puntaje",IF(U7<=10,"Poco valor estratégico",IF(U7<=15,"Torta débil",IF(U7<=20,"Buena torta","Excelente torta"))))) -> Revisar puntaje
A8: 4 | B8: =IF('Inventario del Portafolio'!B9="","",'Inventario del Portafolio'!B9) | C8: =IF(B8="","",'Inventario del Portafolio'!E9) | D8: =IF(B8="","",'Inventario del Portafolio'!J9) | E8: =IF(B8="","",'Índice PAN'!H8) | F8: =IF(B8="","",'Índice PAN'!I8) | G8: =IF(B8="","",'Índice TORTA'!H8) | H8: =IF(B8="","",'Índice TORTA'!I8) | I8: =IF(B8="","",IF(OR(E8="",G8=""),"SIN EVALUAR",IF(AND(E8>=16,G8>=16),"ESTRELLA",IF(AND(E8>=16,G8<16),"PAN",IF(AND(E8<16,G8>=16),"TORTA","LASTRE"))))) | J8: =IF(I8="","",IF(I8="ESTRELLA","Escalar y proteger",IF(I8="PAN","Conectar con una TORTA",IF(I8="TORTA","Crear un PAN de entrada",IF(I8="LASTRE","Rediseñar o retirar","Completar evaluación"))))) | K8: =IF(B8="","",IF(I8="ESTRELLA","1 - Alta",IF(I8="PAN","2 - Media",IF(I8="TORTA","2 - Media",IF(I8="LASTRE","1 - Alta","3 - Pendiente"))))) | N8: =SUM(I8:M8) -> 0 | O8: =IF(N8="","",IF(N8<5,"Revisar puntaje",IF(N8<=10,"No funciona como pan",IF(N8<=15,"Pan débil",IF(N8<=20,"Buen producto pan","Excelente producto pan"))))) -> Revisar puntaje | U8: =SUM(P8:T8) -> 0 | V8: =IF(U8="","",IF(U8<5,"Revisar puntaje",IF(U8<=10,"Poco valor estratégico",IF(U8<=15,"Torta débil",IF(U8<=20,"Buena torta","Excelente torta"))))) -> Revisar puntaje
A9: 5 | B9: =IF('Inventario del Portafolio'!B10="","",'Inventario del Portafolio'!B10) | C9: =IF(B9="","",'Inventario del Portafolio'!E10) | D9: =IF(B9="","",'Inventario del Portafolio'!J10) | E9: =IF(B9="","",'Índice PAN'!H9) | F9: =IF(B9="","",'Índice PAN'!I9) | G9: =IF(B9="","",'Índice TORTA'!H9) | H9: =IF(B9="","",'Índice TORTA'!I9) | I9: =IF(B9="","",IF(OR(E9="",G9=""),"SIN EVALUAR",IF(AND(E9>=16,G9>=16),"ESTRELLA",IF(AND(E9>=16,G9<16),"PAN",IF(AND(E9<16,G9>=16),"TORTA","LASTRE"))))) | J9: =IF(I9="","",IF(I9="ESTRELLA","Escalar y proteger",IF(I9="PAN","Conectar con una TORTA",IF(I9="TORTA","Crear un PAN de entrada",IF(I9="LASTRE","Rediseñar o retirar","Completar evaluación"))))) | K9: =IF(B9="","",IF(I9="ESTRELLA","1 - Alta",IF(I9="PAN","2 - Media",IF(I9="TORTA","2 - Media",IF(I9="LASTRE","1 - Alta","3 - Pendiente"))))) | N9: =SUM(I9:M9) -> 0 | O9: =IF(N9="","",IF(N9<5,"Revisar puntaje",IF(N9<=10,"No funciona como pan",IF(N9<=15,"Pan débil",IF(N9<=20,"Buen producto pan","Excelente producto pan"))))) -> Revisar puntaje | U9: =SUM(P9:T9) -> 0 | V9: =IF(U9="","",IF(U9<5,"Revisar puntaje",IF(U9<=10,"Poco valor estratégico",IF(U9<=15,"Torta débil",IF(U9<=20,"Buena torta","Excelente torta"))))) -> Revisar puntaje
A10: 6 | B10: =IF('Inventario del Portafolio'!B11="","",'Inventario del Portafolio'!B11) | C10: =IF(B10="","",'Inventario del Portafolio'!E11) | D10: =IF(B10="","",'Inventario del Portafolio'!J11) | E10: =IF(B10="","",'Índice PAN'!H10) | F10: =IF(B10="","",'Índice PAN'!I10) | G10: =IF(B10="","",'Índice TORTA'!H10) | H10: =IF(B10="","",'Índice TORTA'!I10) | I10: =IF(B10="","",IF(OR(E10="",G10=""),"SIN EVALUAR",IF(AND(E10>=16,G10>=16),"ESTRELLA",IF(AND(E10>=16,G10<16),"PAN",IF(AND(E10<16,G10>=16),"TORTA","LASTRE"))))) | J10: =IF(I10="","",IF(I10="ESTRELLA","Escalar y proteger",IF(I10="PAN","Conectar con una TORTA",IF(I10="TORTA","Crear un PAN de entrada",IF(I10="LASTRE","Rediseñar o retirar","Completar evaluación"))))) | K10: =IF(B10="","",IF(I10="ESTRELLA","1 - Alta",IF(I10="PAN","2 - Media",IF(I10="TORTA","2 - Media",IF(I10="LASTRE","1 - Alta","3 - Pendiente"))))) | N10: =SUM(I10:M10) -> 0 | O10: =IF(N10="","",IF(N10<5,"Revisar puntaje",IF(N10<=10,"No funciona como pan",IF(N10<=15,"Pan débil",IF(N10<=20,"Buen producto pan","Excelente producto pan"))))) -> Revisar puntaje | U10: =SUM(P10:T10) -> 0 | V10: =IF(U10="","",IF(U10<5,"Revisar puntaje",IF(U10<=10,"Poco valor estratégico",IF(U10<=15,"Torta débil",IF(U10<=20,"Buena torta","Excelente torta"))))) -> Revisar puntaje
A11: 7 | B11: =IF('Inventario del Portafolio'!B12="","",'Inventario del Portafolio'!B12) | C11: =IF(B11="","",'Inventario del Portafolio'!E12) | D11: =IF(B11="","",'Inventario del Portafolio'!J12) | E11: =IF(B11="","",'Índice PAN'!H11) | F11: =IF(B11="","",'Índice PAN'!I11) | G11: =IF(B11="","",'Índice TORTA'!H11) | H11: =IF(B11="","",'Índice TORTA'!I11) | I11: =IF(B11="","",IF(OR(E11="",G11=""),"SIN EVALUAR",IF(AND(E11>=16,G11>=16),"ESTRELLA",IF(AND(E11>=16,G11<16),"PAN",IF(AND(E11<16,G11>=16),"TORTA","LASTRE"))))) | J11: =IF(I11="","",IF(I11="ESTRELLA","Escalar y proteger",IF(I11="PAN","Conectar con una TORTA",IF(I11="TORTA","Crear un PAN de entrada",IF(I11="LASTRE","Rediseñar o retirar","Completar evaluación"))))) | K11: =IF(B11="","",IF(I11="ESTRELLA","1 - Alta",IF(I11="PAN","2 - Media",IF(I11="TORTA","2 - Media",IF(I11="LASTRE","1 - Alta","3 - Pendiente"))))) | M11: LASTRE Flujo bajo / Valor bajo Rediseñar o retirar | N11: =SUM(I11:M11) -> 0 | O11: =IF(N11="","",IF(N11<5,"Revisar puntaje",IF(N11<=10,"No funciona como pan",IF(N11<=15,"Pan débil",IF(N11<=20,"Buen producto pan","Excelente producto pan"))))) -> Revisar puntaje | Q11: TORTA Flujo bajo / Valor alto Crear un PAN de entrada | U11: =SUM(P11:T11) -> 0 | V11: =IF(U11="","",IF(U11<5,"Revisar puntaje",IF(U11<=10,"Poco valor estratégico",IF(U11<=15,"Torta débil",IF(U11<=20,"Buena torta","Excelente torta"))))) -> Revisar puntaje
A12: 8 | B12: =IF('Inventario del Portafolio'!B13="","",'Inventario del Portafolio'!B13) | C12: =IF(B12="","",'Inventario del Portafolio'!E13) | D12: =IF(B12="","",'Inventario del Portafolio'!J13) | E12: =IF(B12="","",'Índice PAN'!H12) | F12: =IF(B12="","",'Índice PAN'!I12) | G12: =IF(B12="","",'Índice TORTA'!H12) | H12: =IF(B12="","",'Índice TORTA'!I12) | I12: =IF(B12="","",IF(OR(E12="",G12=""),"SIN EVALUAR",IF(AND(E12>=16,G12>=16),"ESTRELLA",IF(AND(E12>=16,G12<16),"PAN",IF(AND(E12<16,G12>=16),"TORTA","LASTRE"))))) | J12: =IF(I12="","",IF(I12="ESTRELLA","Escalar y proteger",IF(I12="PAN","Conectar con una TORTA",IF(I12="TORTA","Crear un PAN de entrada",IF(I12="LASTRE","Rediseñar o retirar","Completar evaluación"))))) | K12: =IF(B12="","",IF(I12="ESTRELLA","1 - Alta",IF(I12="PAN","2 - Media",IF(I12="TORTA","2 - Media",IF(I12="LASTRE","1 - Alta","3 - Pendiente"))))) | N12: =SUM(I12:M12) -> 0 | O12: =IF(N12="","",IF(N12<5,"Revisar puntaje",IF(N12<=10,"No funciona como pan",IF(N12<=15,"Pan débil",IF(N12<=20,"Buen producto pan","Excelente producto pan"))))) -> Revisar puntaje | U12: =SUM(P12:T12) -> 0 | V12: =IF(U12="","",IF(U12<5,"Revisar puntaje",IF(U12<=10,"Poco valor estratégico",IF(U12<=15,"Torta débil",IF(U12<=20,"Buena torta","Excelente torta"))))) -> Revisar puntaje
A13: 9 | B13: =IF('Inventario del Portafolio'!B14="","",'Inventario del Portafolio'!B14) | C13: =IF(B13="","",'Inventario del Portafolio'!E14) | D13: =IF(B13="","",'Inventario del Portafolio'!J14) | F13: =IF(B13="","",'Índice PAN'!I13) | G13: =IF(B13="","",'Índice TORTA'!H13) | H13: =IF(B13="","",'Índice TORTA'!I13) | I13: =IF(B13="","",IF(OR(E13="",G13=""),"SIN EVALUAR",IF(AND(E13>=16,G13>=16),"ESTRELLA",IF(AND(E13>=16,G13<16),"PAN",IF(AND(E13<16,G13>=16),"TORTA","LASTRE"))))) | J13: =IF(I13="","",IF(I13="ESTRELLA","Escalar y proteger",IF(I13="PAN","Conectar con una TORTA",IF(I13="TORTA","Crear un PAN de entrada",IF(I13="LASTRE","Rediseñar o retirar","Completar evaluación"))))) | K13: =IF(B13="","",IF(I13="ESTRELLA","1 - Alta",IF(I13="PAN","2 - Media",IF(I13="TORTA","2 - Media",IF(I13="LASTRE","1 - Alta","3 - Pendiente"))))) | N13: =SUM(I13:M13) -> 0 | O13: =IF(N13="","",IF(N13<5,"Revisar puntaje",IF(N13<=10,"No funciona como pan",IF(N13<=15,"Pan débil",IF(N13<=20,"Buen producto pan","Excelente producto pan"))))) -> Revisar puntaje | U13: =SUM(P13:T13) -> 0 | V13: =IF(U13="","",IF(U13<5,"Revisar puntaje",IF(U13<=10,"Poco valor estratégico",IF(U13<=15,"Torta débil",IF(U13<=20,"Buena torta","Excelente torta"))))) -> Revisar puntaje
A14: 10 | B14: =IF('Inventario del Portafolio'!B15="","",'Inventario del Portafolio'!B15) | C14: =IF(B14="","",'Inventario del Portafolio'!E15) | D14: =IF(B14="","",'Inventario del Portafolio'!J15) | F14: =IF(B14="","",'Índice PAN'!I14) | G14: =IF(B14="","",'Índice TORTA'!H14) | H14: =IF(B14="","",'Índice TORTA'!I14) | I14: =IF(B14="","",IF(OR(E14="",G14=""),"SIN EVALUAR",IF(AND(E14>=16,G14>=16),"ESTRELLA",IF(AND(E14>=16,G14<16),"PAN",IF(AND(E14<16,G14>=16),"TORTA","LASTRE"))))) | J14: =IF(I14="","",IF(I14="ESTRELLA","Escalar y proteger",IF(I14="PAN","Conectar con una TORTA",IF(I14="TORTA","Crear un PAN de entrada",IF(I14="LASTRE","Rediseñar o retirar","Completar evaluación"))))) | K14: =IF(B14="","",IF(I14="ESTRELLA","1 - Alta",IF(I14="PAN","2 - Media",IF(I14="TORTA","2 - Media",IF(I14="LASTRE","1 - Alta","3 - Pendiente"))))) | N14: =SUM(I14:M14) -> 0 | O14: =IF(N14="","",IF(N14<5,"Revisar puntaje",IF(N14<=10,"No funciona como pan",IF(N14<=15,"Pan débil",IF(N14<=20,"Buen producto pan","Excelente producto pan"))))) -> Revisar puntaje | U14: =SUM(P14:T14) -> 0 | V14: =IF(U14="","",IF(U14<5,"Revisar puntaje",IF(U14<=10,"Poco valor estratégico",IF(U14<=15,"Torta débil",IF(U14<=20,"Buena torta","Excelente torta"))))) -> Revisar puntaje
H16: CUADRANTE | I16: N.º PRODUCTOS
H17: ESTRELLA | I17: =COUNTIF(I5:I14,"ESTRELLA") -> 0
H18: PAN | I18: =COUNTIF(I5:I14,"PAN") -> 0
H19: TORTA | I19: =COUNTIF(I5:I14,"TORTA") -> 0
H20: LASTRE | I20: =COUNTIF(I5:I14,"LASTRE") -> 0

Sheet Economía del producto
A1: ECONOMÍA DEL PRODUCTO
A2: Compara tres ofertas clave. No confundas facturación con contribución real. | D2: HERRAMIENTA 3
A4: VARIABLE | B4: PRODUCTO 1 | C4: PRODUCTO 2 | D4: PRODUCTO 3
A5: Producto seleccionado
A6: Precio promedio | B6: =IFERROR(INDEX('Inventario del Portafolio'!$C$6:$C$15,MATCH(B$5,'Inventario del Portafolio'!$B$6:$B$15,0)),"") | C6: =IFERROR(INDEX('Inventario del Portafolio'!$C$6:$C$15,MATCH(C$5,'Inventario del Portafolio'!$B$6:$B$15,0)),"") | D6: =IFERROR(INDEX('Inventario del Portafolio'!$C$6:$C$15,MATCH(D$5,'Inventario del Portafolio'!$B$6:$B$15,0)),"")
A7: Ventas mensuales | B7: =IFERROR(INDEX('Inventario del Portafolio'!$D$6:$D$15,MATCH(B$5,'Inventario del Portafolio'!$B$6:$B$15,0)),"") | C7: =IFERROR(INDEX('Inventario del Portafolio'!$D$6:$D$15,MATCH(C$5,'Inventario del Portafolio'!$B$6:$B$15,0)),"") | D7: =IFERROR(INDEX('Inventario del Portafolio'!$D$6:$D$15,MATCH(D$5,'Inventario del Portafolio'!$B$6:$B$15,0)),"")
A8: Facturación mensual | B8: =IF(OR(B6="",B7=""),"",B6*B7) | C8: =IF(OR(C6="",C7=""),"",C6*C7) | D8: =IF(OR(D6="",D7=""),"",D6*D7)
A9: Costo directo unitario
A10: Costos directos mensuales | B10: =IF(OR(B7="",B9=""),"",B7*B9) | C10: =IF(OR(C7="",C9=""),"",C7*C9) | D10: =IF(OR(D7="",D9=""),"",D7*D9)
A11: Horas de entrega por unidad | B11: =IFERROR(INDEX('Inventario del Portafolio'!$G$6:$G$15,MATCH(B$5,'Inventario del Portafolio'!$B$6:$B$15,0)),"") | C11: =IFERROR(INDEX('Inventario del Portafolio'!$G$6:$G$15,MATCH(C$5,'Inventario del Portafolio'!$B$6:$B$15,0)),"") | D11: =IFERROR(INDEX('Inventario del Portafolio'!$G$6:$G$15,MATCH(D$5,'Inventario del Portafolio'!$B$6:$B$15,0)),"")
A12: Horas mensuales | B12: =IF(OR(B7="",B11=""),"",B7*B11) | C12: =IF(OR(C7="",C11=""),"",C7*C11) | D12: =IF(OR(D7="",D11=""),"",D7*D11)
A13: Costo por hora
A14: Costo total de horas | B14: =IF(OR(B12="",B13=""),"",B12*B13) | C14: =IF(OR(C12="",C13=""),"",C12*C13) | D14: =IF(OR(D12="",D13=""),"",D12*D13)
A15: Retrabajo / devoluciones mensuales
A16: Margen de contribución | B16: =IF(B8="","",B8-B10-B14-B15) | C16: =IF(C8="","",C8-C10-C14-C15) | D16: =IF(D8="","",D8-D10-D14-D15)
A17: Margen de contribución % | B17: =IF(OR(B16="",B8=""),"",B16/B8) | C17: =IF(OR(C16="",C8=""),"",C16/C8) | D17: =IF(OR(D16="",D8=""),"",D16/D8)
A18: Margen por hora | B18: =IF(OR(B16="",B12=""),"",IFERROR(B16/B12,0)) | C18: =IF(OR(C16="",C12=""),"",IFERROR(C16/C12,0)) | D18: =IF(OR(D16="",D12=""),"",IFERROR(D16/D12,0))
A19: Tasa de recompra
A20: % clientes que compran otra oferta
A21: Genera caja (1–5)
A22: Genera confianza (1–5)
A23: Genera clientes (1–5)
A24: Genera margen (1–5)
A25: Puntaje estratégico | B25: =IF(COUNT(B21:B24)<4,"",SUM(B21:B24)) | C25: =IF(COUNT(C21:C24)<4,"",SUM(C21:C24)) | D25: =IF(COUNT(D21:D24)<4,"",SUM(D21:D24))
A26: Diagnóstico | B26: =IF(B25="","Completa los cuatro puntajes",IF(B25<=8,"Economía débil",IF(B25<=12,"Economía frágil",IF(B25<=16,"Economía saludable","Motor económico")))) -> Completa los cuatro puntajes | C26: =IF(C25="","Completa los cuatro puntajes",IF(C25<=8,"Economía débil",IF(C25<=12,"Economía frágil",IF(C25<=16,"Economía saludable","Motor económico")))) -> Completa los cuatro puntajes | D26: =IF(D25="","Completa los cuatro puntajes",IF(D25<=8,"Economía débil",IF(D25<=12,"Economía frágil",IF(D25<=16,"Economía saludable","Motor económico")))) -> Completa los cuatro puntajes

Sheet Canvas Producto PAN
A1: CANVAS DEL PRODUCTO PAN
A2: Diseña una oferta fácil de entender, de bajo riesgo y con una ruta explícita hacia una TORTA. | J2: HERRAMIENTA 7
A3: PRODUCTO PAN A DISEÑAR | G3: TORTA A LA QUE DEBE CONDUCIR
A6: CLIENTE IDEAL | G6: PROBLEMA ESPECÍFICO Y URGENTE
A10: RESULTADO PROMETIDO | G10: TIEMPO HASTA EL RESULTADO | J10: PRECIO DE ENTRADA
A14: QUÉ INCLUYE / FORMATO | G14: QUÉ ELIMINA EL RIESGO | J14: EVIDENCIA QUE GENERA CONFIANZA
A18: QUÉ NO INCLUYE | G18: PRÓXIMA TORTA
A22: CTA / SIGUIENTE PASO | G22: CAPACIDAD MÁXIMA MENSUAL | J22: RESPONSABLE
A26: EXPERIMENTO DE 30 DÍAS | I26: MÉTRICA | K26: UMBRAL DE ÉXITO
A31: NIVEL DE COMPLETITUD DEL CANVAS | I31: =(--(A4<>"")+--(G4<>"")+--(A7<>"")+--(G7<>"")+--(A11<>"")+--(G11<>"")+--(J11<>"")+--(A15<>"")+--(G15<>"")+--(J15<>"")+--(A19<>"")+--(G19<>"")+--(A23<>"")+--(G23<>"")+--(J23<>"")+--(A27<>"")+--(I27<>"")+--(K27<>""))/18 -> 0

Sheet Escalera PAN-TORTA
A1: ESCALERA PAN–TORTA
A2: Diseña la secuencia comercial: cada oferta debe resolver algo y abrir naturalmente la siguiente decisión. | H2: HERRAMIENTA 8
A3: PROSPECTOS CALIFICADOS / MES | D3: CONVERSIÓN HASTA LA TORTA | G3: =IF(OR(F6="",F9=""),"",IFERROR(F9/F6,0)) | H3: INGRESO MENSUAL ESPERADO | J3: =SUM(G6:G11) -> 0
A5: NIVEL | B5: ETAPA | C5: OFERTA | D5: PRECIO | E5: CONVERSIÓN DESDE ANTERIOR | F5: CLIENTES ESPERADOS | G5: INGRESO ESPERADO | H5: RESULTADO / PROMESA | I5: SIGUIENTE OFERTA | J5: RESPONSABLE
A6: 0 | B6: Atracción / diagnóstico | G6: =IF(OR(D6="",F6=""),"",D6*F6)
A7: 1 | B7: PAN | F7: =IF(OR(E7="",F6=""),"",F6*E7) | G7: =IF(OR(D7="",F7=""),"",D7*F7)
A8: 2 | B8: PAN puente / recurrencia | F8: =IF(OR(E8="",F7=""),"",F7*E8) | G8: =IF(OR(D8="",F8=""),"",D8*F8)
A9: 3 | B9: TORTA principal | F9: =IF(OR(E9="",F8=""),"",F8*E9) | G9: =IF(OR(D9="",F9=""),"",D9*F9)
A10: 4 | B10: Continuidad | F10: =IF(OR(E10="",F9=""),"",F9*E10) | G10: =IF(OR(D10="",F10=""),"",D10*F10)
A11: 5 | B11: Expansión / referidos | F11: =IF(OR(E11="",F10=""),"",F10*E11) | G11: =IF(OR(D11="",F11=""),"",D11*F11)
A14: REGLA | B14: PREGUNTA DE CONTROL
A15: Sin salto | B15: ¿El cliente entiende por qué la siguiente oferta es el paso lógico después del resultado anterior?
A16: Sin callejón | B16: ¿Cada PAN conduce a una TORTA concreta y medible?

Sheet Capacidad del Horno
A1: CAPACIDAD DEL HORNO
A2: Comprueba si el portafolio puede crecer sin romper la operación ni volver indispensable al fundador. | L2: HERRAMIENTA 9
A3: HORAS DEMANDADAS | D3: CAPACIDAD ÚTIL | G3: UTILIZACIÓN GLOBAL | J3: CUELLOS DE BOTELLA
A4: =SUM(E6:E15) -> 0 | D4: =SUM(K6:K12) -> 0 | G4: =IFERROR(SUM(E6:E15)/SUM(K6:K12),0) -> 0 | J4: =COUNTIF(N6:N12,"SOBRECARGADO")+COUNTIF(N6:N12,"EN RIESGO") -> 0
A5: # | B5: PRODUCTO / SERVICIO | C5: UNIDADES / MES | D5: HORAS / UNIDAD | E5: HORAS MENSUALES | F5: RESPONSABLE | H5: RECURSO / ROL | I5: HORAS DISPONIBLES | J5: RESERVA OPERATIVA | K5: CAPACIDAD ÚTIL | L5: HORAS DEL PORTAFOLIO | M5: UTILIZACIÓN | N5: ESTADO
A6: 1 | B6: =IF('Inventario del Portafolio'!B6="","",'Inventario del Portafolio'!B6) | C6: =IF(B6="","",'Inventario del Portafolio'!D6) | D6: =IF(B6="","",'Inventario del Portafolio'!G6) | E6: =IF(B6="","",'Inventario del Portafolio'!H6) | F6: =IF(B6="","",'Inventario del Portafolio'!I6) | K6: =IF(I6="","",I6*(1-J6)) | L6: =IF(H6="","",SUMIF($F$6:$F$15,H6,$E$6:$E$15)) | M6: =IFERROR(L6/K6,0) -> 0 | N6: =IF(H6="","",IF(M6>1,"SOBRECARGADO",IF(M6>0.85,"EN RIESGO","DISPONIBLE")))
A7: 2 | B7: =IF('Inventario del Portafolio'!B7="","",'Inventario del Portafolio'!B7) | C7: =IF(B7="","",'Inventario del Portafolio'!D7) | D7: =IF(B7="","",'Inventario del Portafolio'!G7) | E7: =IF(B7="","",'Inventario del Portafolio'!H7) | F7: =IF(B7="","",'Inventario del Portafolio'!I7) | K7: =IF(I7="","",I7*(1-J7)) | L7: =IF(H7="","",SUMIF($F$6:$F$15,H7,$E$6:$E$15)) | M7: =IFERROR(L7/K7,0) -> 0 | N7: =IF(H7="","",IF(M7>1,"SOBRECARGADO",IF(M7>0.85,"EN RIESGO","DISPONIBLE")))
A8: 3 | B8: =IF('Inventario del Portafolio'!B8="","",'Inventario del Portafolio'!B8) | C8: =IF(B8="","",'Inventario del Portafolio'!D8) | D8: =IF(B8="","",'Inventario del Portafolio'!G8) | E8: =IF(B8="","",'Inventario del Portafolio'!H8) | F8: =IF(B8="","",'Inventario del Portafolio'!I8) | K8: =IF(I8="","",I8*(1-J8)) | L8: =IF(H8="","",SUMIF($F$6:$F$15,H8,$E$6:$E$15)) | M8: =IFERROR(L8/K8,0) -> 0 | N8: =IF(H8="","",IF(M8>1,"SOBRECARGADO",IF(M8>0.85,"EN RIESGO","DISPONIBLE")))
A9: 4 | B9: =IF('Inventario del Portafolio'!B9="","",'Inventario del Portafolio'!B9) | C9: =IF(B9="","",'Inventario del Portafolio'!D9) | D9: =IF(B9="","",'Inventario del Portafolio'!G9) | E9: =IF(B9="","",'Inventario del Portafolio'!H9) | F9: =IF(B9="","",'Inventario del Portafolio'!I9) | K9: =IF(I9="","",I9*(1-J9)) | L9: =IF(H9="","",SUMIF($F$6:$F$15,H9,$E$6:$E$15)) | M9: =IFERROR(L9/K9,0) -> 0 | N9: =IF(H9="","",IF(M9>1,"SOBRECARGADO",IF(M9>0.85,"EN RIESGO","DISPONIBLE")))
A10: 5 | B10: =IF('Inventario del Portafolio'!B10="","",'Inventario del Portafolio'!B10) | C10: =IF(B10="","",'Inventario del Portafolio'!D10) | D10: =IF(B10="","",'Inventario del Portafolio'!G10) | E10: =IF(B10="","",'Inventario del Portafolio'!H10) | F10: =IF(B10="","",'Inventario del Portafolio'!I10) | K10: =IF(I10="","",I10*(1-J10)) | L10: =IF(H10="","",SUMIF($F$6:$F$15,H10,$E$6:$E$15)) | M10: =IFERROR(L10/K10,0) -> 0 | N10: =IF(H10="","",IF(M10>1,"SOBRECARGADO",IF(M10>0.85,"EN RIESGO","DISPONIBLE")))
A11: 6 | B11: =IF('Inventario del Portafolio'!B11="","",'Inventario del Portafolio'!B11) | C11: =IF(B11="","",'Inventario del Portafolio'!D11) | D11: =IF(B11="","",'Inventario del Portafolio'!G11) | E11: =IF(B11="","",'Inventario del Portafolio'!H11) | F11: =IF(B11="","",'Inventario del Portafolio'!I11) | K11: =IF(I11="","",I11*(1-J11)) | L11: =IF(H11="","",SUMIF($F$6:$F$15,H11,$E$6:$E$15)) | M11: =IFERROR(L11/K11,0) -> 0 | N11: =IF(H11="","",IF(M11>1,"SOBRECARGADO",IF(M11>0.85,"EN RIESGO","DISPONIBLE")))
A12: 7 | B12: =IF('Inventario del Portafolio'!B12="","",'Inventario del Portafolio'!B12) | C12: =IF(B12="","",'Inventario del Portafolio'!D12) | D12: =IF(B12="","",'Inventario del Portafolio'!G12) | E12: =IF(B12="","",'Inventario del Portafolio'!H12) | F12: =IF(B12="","",'Inventario del Portafolio'!I12) | K12: =IF(I12="","",I12*(1-J12)) | L12: =IF(H12="","",SUMIF($F$6:$F$15,H12,$E$6:$E$15)) | M12: =IFERROR(L12/K12,0) -> 0 | N12: =IF(H12="","",IF(M12>1,"SOBRECARGADO",IF(M12>0.85,"EN RIESGO","DISPONIBLE")))
A13: 8 | B13: =IF('Inventario del Portafolio'!B13="","",'Inventario del Portafolio'!B13) | C13: =IF(B13="","",'Inventario del Portafolio'!D13) | D13: =IF(B13="","",'Inventario del Portafolio'!G13) | E13: =IF(B13="","",'Inventario del Portafolio'!H13) | F13: =IF(B13="","",'Inventario del Portafolio'!I13)
A14: 9 | B14: =IF('Inventario del Portafolio'!B14="","",'Inventario del Portafolio'!B14) | C14: =IF(B14="","",'Inventario del Portafolio'!D14) | D14: =IF(B14="","",'Inventario del Portafolio'!G14) | E14: =IF(B14="","",'Inventario del Portafolio'!H14) | F14: =IF(B14="","",'Inventario del Portafolio'!I14)
A15: 10 | B15: =IF('Inventario del Portafolio'!B15="","",'Inventario del Portafolio'!B15) | C15: =IF(B15="","",'Inventario del Portafolio'!D15) | D15: =IF(B15="","",'Inventario del Portafolio'!G15) | E15: =IF(B15="","",'Inventario del Portafolio'!H15) | F15: =IF(B15="","",'Inventario del Portafolio'!I15) | H15: Usa exactamente el mismo nombre del responsable registrado en el Inventario para que las horas se consoliden.

Sheet Dieta del Portafolio
A1: DIETA DEL PORTAFOLIO
A2: Decide qué alimentar, qué mantener y qué dejar de sostener por costumbre. | J2: HERRAMIENTA 10
A3: INGRESO DEL PORTAFOLIO | D3: INGRESO EN ESTRELLAS | G3: INGRESO EN LASTRES | J3: PRODUCTOS A REDISEÑAR / RETIRAR
A4: ='Inventario del Portafolio'!E16 -> 0 | D4: =SUMIF(C6:C15,"ESTRELLA",D6:D15) -> 0 | G4: =SUMIF(C6:C15,"LASTRE",D6:D15) -> 0 | J4: =COUNTIF(G6:G15,"Rediseñar")+COUNTIF(G6:G15,"Retirar") -> 0
A5: # | B5: PRODUCTO / SERVICIO | C5: CUADRANTE | D5: INGRESO MENSUAL | E5: HORAS MENSUALES | F5: RECOMENDACIÓN AUTOMÁTICA | G5: DECISIÓN 90 DÍAS | H5: POR QUÉ | I5: RESULTADO / META | J5: RESPONSABLE | K5: FECHA LÍMITE | L5: ESTADO
A6: 1 | B6: =IF('Inventario del Portafolio'!B6="","",'Inventario del Portafolio'!B6) | C6: =IF(B6="","",'Mapa estratégico'!I5) | D6: =IF(B6="","",'Inventario del Portafolio'!E6) | E6: =IF(B6="","",'Inventario del Portafolio'!H6) | F6: =IF(C6="","",IF(C6="ESTRELLA","Escalar",IF(C6="PAN","Optimizar y conectar",IF(C6="TORTA","Crear PAN de entrada",IF(C6="LASTRE","Rediseñar o retirar","Evaluar")))))
A7: 2 | B7: =IF('Inventario del Portafolio'!B7="","",'Inventario del Portafolio'!B7) | C7: =IF(B7="","",'Mapa estratégico'!I6) | D7: =IF(B7="","",'Inventario del Portafolio'!E7) | E7: =IF(B7="","",'Inventario del Portafolio'!H7) | F7: =IF(C7="","",IF(C7="ESTRELLA","Escalar",IF(C7="PAN","Optimizar y conectar",IF(C7="TORTA","Crear PAN de entrada",IF(C7="LASTRE","Rediseñar o retirar","Evaluar")))))
A8: 3 | B8: =IF('Inventario del Portafolio'!B8="","",'Inventario del Portafolio'!B8) | C8: =IF(B8="","",'Mapa estratégico'!I7) | D8: =IF(B8="","",'Inventario del Portafolio'!E8) | E8: =IF(B8="","",'Inventario del Portafolio'!H8) | F8: =IF(C8="","",IF(C8="ESTRELLA","Escalar",IF(C8="PAN","Optimizar y conectar",IF(C8="TORTA","Crear PAN de entrada",IF(C8="LASTRE","Rediseñar o retirar","Evaluar")))))
A9: 4 | B9: =IF('Inventario del Portafolio'!B9="","",'Inventario del Portafolio'!B9) | C9: =IF(B9="","",'Mapa estratégico'!I8) | D9: =IF(B9="","",'Inventario del Portafolio'!E9) | E9: =IF(B9="","",'Inventario del Portafolio'!H9) | F9: =IF(C9="","",IF(C9="ESTRELLA","Escalar",IF(C9="PAN","Optimizar y conectar",IF(C9="TORTA","Crear PAN de entrada",IF(C9="LASTRE","Rediseñar o retirar","Evaluar")))))
A10: 5 | B10: =IF('Inventario del Portafolio'!B10="","",'Inventario del Portafolio'!B10) | C10: =IF(B10="","",'Mapa estratégico'!I9) | D10: =IF(B10="","",'Inventario del Portafolio'!E10) | E10: =IF(B10="","",'Inventario del Portafolio'!H10) | F10: =IF(C10="","",IF(C10="ESTRELLA","Escalar",IF(C10="PAN","Optimizar y conectar",IF(C10="TORTA","Crear PAN de entrada",IF(C10="LASTRE","Rediseñar o retirar","Evaluar")))))
A11: 6 | B11: =IF('Inventario del Portafolio'!B11="","",'Inventario del Portafolio'!B11) | C11: =IF(B11="","",'Mapa estratégico'!I10) | D11: =IF(B11="","",'Inventario del Portafolio'!E11) | E11: =IF(B11="","",'Inventario del Portafolio'!H11) | F11: =IF(C11="","",IF(C11="ESTRELLA","Escalar",IF(C11="PAN","Optimizar y conectar",IF(C11="TORTA","Crear PAN de entrada",IF(C11="LASTRE","Rediseñar o retirar","Evaluar")))))
A12: 7 | B12: =IF('Inventario del Portafolio'!B12="","",'Inventario del Portafolio'!B12) | C12: =IF(B12="","",'Mapa estratégico'!I11) | D12: =IF(B12="","",'Inventario del Portafolio'!E12) | E12: =IF(B12="","",'Inventario del Portafolio'!H12) | F12: =IF(C12="","",IF(C12="ESTRELLA","Escalar",IF(C12="PAN","Optimizar y conectar",IF(C12="TORTA","Crear PAN de entrada",IF(C12="LASTRE","Rediseñar o retirar","Evaluar")))))
A13: 8 | B13: =IF('Inventario del Portafolio'!B13="","",'Inventario del Portafolio'!B13) | C13: =IF(B13="","",'Mapa estratégico'!I12) | D13: =IF(B13="","",'Inventario del Portafolio'!E13) | E13: =IF(B13="","",'Inventario del Portafolio'!H13) | F13: =IF(C13="","",IF(C13="ESTRELLA","Escalar",IF(C13="PAN","Optimizar y conectar",IF(C13="TORTA","Crear PAN de entrada",IF(C13="LASTRE","Rediseñar o retirar","Evaluar")))))
A14: 9 | B14: =IF('Inventario del Portafolio'!B14="","",'Inventario del Portafolio'!B14) | C14: =IF(B14="","",'Mapa estratégico'!I13) | D14: =IF(B14="","",'Inventario del Portafolio'!E14) | E14: =IF(B14="","",'Inventario del Portafolio'!H14) | F14: =IF(C14="","",IF(C14="ESTRELLA","Escalar",IF(C14="PAN","Optimizar y conectar",IF(C14="TORTA","Crear PAN de entrada",IF(C14="LASTRE","Rediseñar o retirar","Evaluar")))))
A15: 10 | B15: =IF('Inventario del Portafolio'!B15="","",'Inventario del Portafolio'!B15) | C15: =IF(B15="","",'Mapa estratégico'!I14) | D15: =IF(B15="","",'Inventario del Portafolio'!E15) | E15: =IF(B15="","",'Inventario del Portafolio'!H15) | F15: =IF(C15="","",IF(C15="ESTRELLA","Escalar",IF(C15="PAN","Optimizar y conectar",IF(C15="TORTA","Crear PAN de entrada",IF(C15="LASTRE","Rediseñar o retirar","Evaluar")))))

Sheet Plan 30D
A1: PLAN DE ACCIÓN 30D
A2: No más de tres prioridades. Cada una debe tener resultado, indicador, responsable y evidencia. | H2: HERRAMIENTA 11
A3: AVANCE DEL PLAN | D3: =IFERROR(AVERAGE(H12:H23),0) -> 0 | E3: ACCIONES COMPLETADAS | H3: =COUNTIF(G12:G23,"Completado") -> 0 | I3: BLOQUEADAS | J3: =COUNTIF(G12:G23,"Bloqueado") -> 0
A5: PRIORIDAD | B5: PROBLEMA QUE RESUELVE | C5: RESULTADO EN 30 DÍAS | D5: INDICADOR | E5: LÍNEA BASE | F5: META | G5: RESPONSABLE | H5: ESTADO | I5: AVANCE | J5: REVISIÓN
A6: 1
A7: 2
A8: 3
A11: SEMANA | B11: PRIORIDAD | C11: ACCIÓN | D11: ENTREGABLE / EVIDENCIA | E11: FECHA LÍMITE | F11: RESPONSABLE | G11: ESTADO | H11: AVANCE | I11: BLOQUEADOR | J11: SIGUIENTE PASO
A12: 1 | B12: 1 | H12: 0
A13: 1 | B13: 2 | H13: 0
A14: 1 | B14: 3 | H14: 0
A15: 2 | B15: 1 | H15: 0
A16: 2 | B16: 2 | H16: 0
A17: 2 | B17: 3 | H17: 0
A18: 3 | B18: 1 | H18: 0
A19: 3 | B19: 2 | H19: 0
A20: 3 | B20: 3 | H20: 0
A21: 4 | B21: 1 | H21: 0
A22: 4 | B22: 2 | H22: 0
A23: 4 | B23: 3 | H23: 0

Sheet Dashboard Ejecutivo
A1: DASHBOARD EJECUTIVO — PAN Y TORTAS
A2: Una sola vista para decidir: flujo, valor, capacidad y ejecución. | L2: HERRAMIENTA 12 | P2: CUADRANTE | Q2: N.º
A3: FRAGILIDAD COMERCIAL | E3: INGRESO MENSUAL | H3: CONCENTRACIÓN MAYOR | K3: HORAS MENSUALES | P3: ESTRELLA | Q3: =COUNTIF('Mapa estratégico'!I5:I14,"ESTRELLA") -> 0
A4: =IF('Indice de fragilidad'!D13="","",'Indice de fragilidad'!D13) | C4: ='Indice de fragilidad'!C13 -> Completa las 9 respuestas | E4: ='Inventario del Portafolio'!E16 -> 0 | H4: =IFERROR(MAX('Inventario del Portafolio'!J6:J15),0) -> 0 | K4: ='Inventario del Portafolio'!H16 -> 0 | P4: PAN | Q4: =COUNTIF('Mapa estratégico'!I5:I14,"PAN") -> 0
P5: TORTA | Q5: =COUNTIF('Mapa estratégico'!I5:I14,"TORTA") -> 0
P6: LASTRE | Q6: =COUNTIF('Mapa estratégico'!I5:I14,"LASTRE") -> 0
A8: ESTRELLAS | D8: PAN | G8: TORTAS | J8: LASTRES | M8: SIN EVALUAR
A9: =COUNTIF('Mapa estratégico'!I5:I14,"ESTRELLA") -> 0 | D9: =COUNTIF('Mapa estratégico'!I5:I14,"PAN") -> 0 | G9: =COUNTIF('Mapa estratégico'!I5:I14,"TORTA") -> 0 | J9: =COUNTIF('Mapa estratégico'!I5:I14,"LASTRE") -> 0 | M9: =COUNTIF('Mapa estratégico'!I5:I14,"SIN EVALUAR") -> 0 | P9: PRODUCTO | Q9: INGRESO
P10: =IF('Inventario del Portafolio'!B6="","",'Inventario del Portafolio'!B6) | Q10: =IF(P10="","",'Inventario del Portafolio'!E6)
P11: =IF('Inventario del Portafolio'!B7="","",'Inventario del Portafolio'!B7) | Q11: =IF(P11="","",'Inventario del Portafolio'!E7)
P12: =IF('Inventario del Portafolio'!B8="","",'Inventario del Portafolio'!B8) | Q12: =IF(P12="","",'Inventario del Portafolio'!E8)
A13: CAPACIDAD ÚTIL | D13: UTILIZACIÓN | G13: CUELLOS DE BOTELLA | J13: AVANCE PLAN 30D | M13: ACCIONES BLOQUEADAS | P13: =IF('Inventario del Portafolio'!B9="","",'Inventario del Portafolio'!B9) | Q13: =IF(P13="","",'Inventario del Portafolio'!E9)
A14: ='Capacidad del Horno'!D4 -> 0 | D14: ='Capacidad del Horno'!G4 -> 0 | G14: ='Capacidad del Horno'!J4 -> 0 | J14: ='Plan 30D'!D3 -> 0 | M14: ='Plan 30D'!J3 -> 0 | P14: =IF('Inventario del Portafolio'!B10="","",'Inventario del Portafolio'!B10) | Q14: =IF(P14="","",'Inventario del Portafolio'!E10)
P15: =IF('Inventario del Portafolio'!B11="","",'Inventario del Portafolio'!B11) | Q15: =IF(P15="","",'Inventario del Portafolio'!E11)
P16: =IF('Inventario del Portafolio'!B12="","",'Inventario del Portafolio'!B12) | Q16: =IF(P16="","",'Inventario del Portafolio'!E12)
P17: =IF('Inventario del Portafolio'!B13="","",'Inventario del Portafolio'!B13) | Q17: =IF(P17="","",'Inventario del Portafolio'!E13)
A18: DECISIONES QUE NO DEBERÍAN ESPERAR | P18: =IF('Inventario del Portafolio'!B14="","",'Inventario del Portafolio'!B14) | Q18: =IF(P18="","",'Inventario del Portafolio'!E14)
A19: MEJOR CANDIDATO A ESCALAR | D19: =IFERROR(INDEX('Mapa estratégico'!B5:B14,MATCH("ESTRELLA",'Mapa estratégico'!I5:I14,0)),"No hay ESTRELLA evaluada") -> No hay ESTRELLA evaluada | H19: LASTRE QUE EXIGE DECISIÓN | K19: =IFERROR(INDEX('Mapa estratégico'!B5:B14,MATCH("LASTRE",'Mapa estratégico'!I5:I14,0)),"No hay LASTRE evaluado") -> No hay LASTRE evaluado | P19: =IF('Inventario del Portafolio'!B15="","",'Inventario del Portafolio'!B15) | Q19: =IF(P19="","",'Inventario del Portafolio'!E15)
A20: PRIORIDAD PRINCIPAL 30D | D20: =IF('Plan 30D'!C6="","Definir la primera prioridad del plan",'Plan 30D'!C6) -> Definir la primera prioridad del plan

Sheet Guía 4H
A1: GUÍA DE FACILITACIÓN — TALLER PAN Y TORTAS (4 HORAS)
A2: Objetivo: que cada participante salga con una primera versión de su journey interno de clientes, detecte vacíos entre PAN y TORTA y defina un experimento de 30 días.
A4: Bloque | B4: Tiempo | C4: Objetivo pedagógico | D4: Herramientas Excel | E4: Dinámica | F4: Pregunta potente | G4: Entregable | H4: Riesgo del facilitador | I4: Adaptación para participantes | J4: Criterio de avance | K4: Notas
A5: Apertura y marco mental | B5: 0:00–0:15 | C5: Instalar la metáfora: no se trata de tener más productos, sino un recorrido que haga avanzar la confianza. | D5: Presentación | E5: Mini historia + pregunta detonadora | F5: ¿Qué pasaría si mañana dejaras de vender tu producto más caro? | G5: Dolor principal escrito | H5: Irse a teoría antes de tocar negocio real | I5: Usar ejemplos simples: contador, estética, consultor, restaurante | J5: Todos identifican una TORTA actual | K5: No explicar todavía todo el modelo; crear tensión.
A6: Diagnóstico de fragilidad | B6: 0:15–0:35 | C6: Hacer visible si el negocio depende de cierres aislados, confianza personal o ventas complejas. | D6: Índice de fragilidad | E6: Autoevaluación individual + lectura por rangos | F6: ¿Tu negocio vende mucho o vende de manera saludable? | G6: Puntaje y foco de rediseño | H6: Que respondan “idealmente” y no con realidad | I6: Pedir responder con el último mes, no con deseos | J6: Puntaje calculado y una frase de diagnóstico | K6: Validar que no es examen: es espejo.
A7: Inventario del portafolio | B7: 0:35–1:05 | C7: Ordenar productos/servicios actuales por ingreso, horas, recurrencia y rol preliminar. | D7: Inventario del Portafolio | E7: Llenado guiado de máximo 10 ofertas | F7: ¿Qué producto te da dinero y cuál te compra tiempo o confianza? | G7: Lista de ofertas actuales | H7: Llenar demasiados productos secundarios | I7: Pedir agrupar variantes parecidas | J7: 8–10 ofertas visibles con ingreso y horas | K7: Corregir nombres: usar el mismo nombre en hojas siguientes.
A8: Economía y rol estratégico | B8: 1:05–1:35 | C8: Separar facturación de contribución real: caja, margen, clientes, confianza y capacidad. | D8: Economía del producto + Índice PAN + Índice TORTA | E8: Evaluar 3 ofertas críticas y luego puntuar portafolio | F8: ¿Qué oferta parece buena, pero consume el horno? | G8: Puntajes PAN/TORTA | H8: Quedarse atrapados en números exactos | I8: Aceptar estimaciones razonables si no tienen data | J8: Al menos 3 ofertas evaluadas con diagnóstico | K8: Priorizar criterio sobre precisión contable perfecta.
A9: Mapa del portafolio | B9: 1:35–2:00 | C9: Ubicar ofertas en ESTRELLA, PAN, TORTA o LASTRE y tomar decisiones iniciales. | D9: Mapa estratégico | E9: Lectura de cuadrantes + conversación en pares | F9: ¿Qué falta entre lo que atrae y lo que realmente quieres vender? | G9: Primer mapa de decisiones | H9: Defender productos por apego emocional | I9: Preguntar por evidencia, no por cariño al producto | J9: Una oferta a escalar y una a rediseñar/retirar | K9: Aquí aparece el gap del journey.
A10: Pausa | B10: 2:00–2:10 | C10: Descanso breve para evitar saturación cognitiva. | D10: — | E10: Pausa activa | F10: — | G10: Energía recuperada | H10: Alargar la pausa | I10: Avisar hora exacta de retorno | J10: Retorno puntual | K10: Reiniciar con una idea: “ahora diseñamos el puente”.
A11: Diseño del PAN | B11: 2:10–2:45 | C11: Diseñar o rediseñar una oferta de entrada clara, segura y conectada a una TORTA. | D11: Canvas Producto PAN | E11: Trabajo individual + revisión rápida | F11: ¿Qué resultado pequeño debe vivir el cliente para confiar en la TORTA? | G11: Canvas PAN completo | H11: Diseñar un PAN barato pero inútil | I11: Enfatizar resultado, riesgo y siguiente paso | J11: Canvas con promesa, precio, riesgo y CTA | K11: No permitir PAN sin TORTA de destino.
A12: Journey / escalera PAN–TORTA | B12: 2:45–3:20 | C12: Convertir productos aislados en una secuencia: atracción, entrada, confianza, resultado, torta, continuidad. | D12: Journey Cliente + Escalera PAN-TORTA | E12: Mapa visual del recorrido + simulación verbal | F12: ¿Cuál es la siguiente decisión natural del cliente después de cada resultado? | G12: Journey de 5–6 niveles | H12: Confundir escalera con lista de precios | I12: Pedir que cada peldaño responda una pregunta del cliente | J12: Recorrido sin saltos ni callejones | K12: Usar lenguaje del cliente, no del negocio.
A13: Capacidad y dieta | B13: 3:20–3:40 | C13: Verificar si el portafolio puede crecer sin saturar al fundador o al equipo. | D13: Capacidad del Horno + Dieta del Portafolio | E13: Revisión de horas + decisiones de dieta | F13: ¿Qué producto te hace crecer y cuál solo te ocupa? | G13: Decisiones: eliminar, fusionar, mantener, escalar | H13: Querer escalar todo | I13: Pedir escoger máximo 3 prioridades | J13: Lista de decisiones 90 días | K13: Conectar a delegación y estandarización.
A14: Plan de 30 días | B14: 3:40–4:00 | C14: Bajar el diseño a una prueba concreta, medible y accionable. | D14: Plan 30D + Dashboard | E14: Compromiso público + métrica mínima | F14: ¿Qué vas a probar antes de construir? | G14: Experimento y primera acción | H14: Salir con inspiración sin implementación | I14: Exigir responsable, fecha y evidencia | J14: Tres prioridades y primera semana definida | K14: Cerrar con compromiso y foto del plan.

Sheet Journey Cliente
A1: JOURNEY INTERNO DEL CLIENTE — DEL PAN A LA TORTA
A2: Diseña el recorrido desde el primer contacto hasta la oferta de mayor valor. Cada paso debe reducir riesgo, aumentar confianza y abrir la siguiente decisión.
A4: Nivel | B4: Momento del cliente | C4: Pregunta interna del cliente | D4: Producto/servicio actual o faltante | E4: Tipo | F4: Promesa / resultado visible | G4: Riesgo que reduce | H4: Prueba de confianza | I4: Precio | J4: Tiempo al resultado | K4: Conversión esperada | L4: Oferta siguiente | M4: Gap detectado | N4: Decisión
A5: 0 | B5: Atracción | C5: ¿Esto es para mí? | E5: Contenido / diagnóstico | F5: Claridad del problema | G5: Riesgo de no entender | H5: Checklist, test, webinar, caso | I5: 0 | J5: Inmediato | L5: PAN | N5: Crear / mejorar
A6: 1 | B6: Primera compra | C6: ¿Puedo probar sin apostar demasiado? | E6: PAN | F6: Resultado pequeño, específico y rápido | G6: Riesgo económico y de confianza | H6: Garantía, muestra, taller, piloto | J6: 1–7 días | L6: PAN puente o TORTA | N6: Crear / mejorar
A7: 2 | B7: Activación / confianza | C7: ¿Me funcionó y me entienden? | E7: PAN puente | F7: Evidencia de avance | G7: Riesgo de continuidad | H7: Indicador, diagnóstico, entregable usable | J7: 7–30 días | L7: TORTA | N7: Crear / mejorar
A8: 3 | B8: Transformación | C8: ¿Vale la pena invertir más? | E8: TORTA | F8: Resultado de mayor valor | G8: Riesgo de implementación | H8: Plan, metodología, casos, seguimiento | J8: 30–120 días | L8: Continuidad | N8: Optimizar
A9: 4 | B9: Continuidad | C9: ¿Cómo sostengo y mejoro esto? | E9: Recurrencia | F9: Acompañamiento o mantenimiento | G9: Riesgo de retroceder | H9: Reportes, reuniones, métricas | J9: Mensual | L9: Expansión / referido | N9: Mantener / escalar
A10: 5 | B10: Expansión / referido | C10: ¿Qué más puedo resolver o a quién puedo recomendar? | E10: Expansión | F10: Nueva necesidad o recomendación | G10: Riesgo de estancamiento | H10: Testimonio, comunidad, referidos | J10: Variable | L10: Nueva necesidad | N10: Escalar
A12: REGLAS DE CALIDAD DEL JOURNEY
A13: 1 | B13: Sin salto | C13: El cliente debe entender por qué el siguiente paso es lógico después del resultado anterior.
A14: 2 | B14: Sin callejón | C14: Ningún PAN debe terminar en sí mismo: debe conducir a una TORTA concreta.
A15: 3 | B15: Sin producto fantasma | C15: Si falta un peldaño, marcarlo como producto faltante y convertirlo en experimento.
A16: 4 | B16: Sin saturar el horno | C16: Antes de escalar, validar horas y responsable.
A17: 5 | B17: Sin promesas vagas | C17: Cada oferta debe entregar un resultado visible, no solo actividades.
